hal/__init__.py
hal/__main__.py
hal/exceptions.py
hal/actor/__init__.py
hal/actor/actor.py
hal/actor/commands/__init__.py
hal/actor/commands/abort_exposures.py
hal/actor/commands/auto_pilot.py
hal/actor/commands/bypass.py
hal/actor/commands/calibrations.py
hal/actor/commands/expose.py
hal/actor/commands/goto.py
hal/actor/commands/goto_field.py
hal/actor/commands/script.py
hal/actor/commands/status.py
hal/actor/commands/test.py
hal/etc/hal.yml
hal/etc/schema.json
hal/etc/scripts/apo/cartchange.inp
hal/etc/scripts/apo/eveningcals.inp
hal/etc/scripts/apo/example.inp
hal/etc/scripts/apo/morningcals.inp
hal/etc/scripts/apo/test.inp
hal/etc/scripts/lco/cartchange.inp
hal/etc/scripts/lco/eveningcals.inp
hal/etc/scripts/lco/morningcals.inp
hal/helpers/__init__.py
hal/helpers/apogee.py
hal/helpers/boss.py
hal/helpers/cherno.py
hal/helpers/ffs.py
hal/helpers/jaeger.py
hal/helpers/lamps.py
hal/helpers/overhead.py
hal/helpers/scripts.py
hal/helpers/tcc.py
hal/macros/__init__.py
hal/macros/apogee_dome_flat.py
hal/macros/auto_pilot.py
hal/macros/expose.py
hal/macros/goto_field.py
hal/macros/macro.py
hal/macros/test_macro.py
sdss_hal-1.4.1.dist-info/METADATA
sdss_hal-1.4.1.dist-info/WHEEL
sdss_hal-1.4.1.dist-info/entry_points.txt
sdss_hal-1.4.1.dist-info/licenses/LICENSE.md
sdss_hal-1.4.1.dist-info/RECORD
