Metadata-Version: 2.4
Name: sdss-hal
Version: 1.4.1
Summary: High-level observing tool for SDSS-V (replaces SOP)
Project-URL: Homepage, https://github.com/sdss/hal
Project-URL: Repository, https://github.com/sdss/hal
Project-URL: Documentation, https://sdss-hal.readthedocs.org
Author-email: José Sánchez-Gallego <gallegoj@uw.edu>
License-Expression: BSD-3-Clause
License-File: LICENSE.md
Requires-Python: <4,>=3.10
Requires-Dist: click-default-group>=1.2.2
Requires-Dist: numpy>=1.22.1
Requires-Dist: peewee>=3.17.0
Requires-Dist: sdss-clu>=2.2.7
Requires-Dist: sdssdb>=0.8.3
Requires-Dist: sdsstools>=1.0.0
Requires-Dist: six>=1.17.0
Requires-Dist: typing-extensions>=4.11.0
